doclean/DoCleanException.py
doclean/__init__.py
doclean/cli.py
doclean-0.1.2.dist-info/licenses/license
doclean-0.1.2.dist-info/METADATA
doclean-0.1.2.dist-info/WHEEL
doclean-0.1.2.dist-info/entry_points.txt
doclean-0.1.2.dist-info/top_level.txt
doclean-0.1.2.dist-info/RECORD
