Metadata-Version: 2.4
Name: doclean
Version: 0.1.2
Summary: Minimal, safe, pyproject.toml-driven cleaning tool for Python projects.
Author: Ed Armstrong
License-Expression: MIT
Project-URL: Homepage, https://github.com/Thaerious/doclean
Classifier: Programming Language :: Python :: 3
Classifier: Programming Language :: Python :: 3.11
Classifier: Programming Language :: Python :: 3.12
Classifier: Operating System :: OS Independent
Requires-Python: >=3.11
License-File: license
Provides-Extra: dev
Requires-Dist: pytest; extra == "dev"
Requires-Dist: pytest-cov; extra == "dev"
Provides-Extra: dependencies
Dynamic: license-file
